local_ffmpeg/__download.py
local_ffmpeg/__init__.py
local_ffmpeg/__main__.py
local_ffmpeg/__platform/__init__.py
local_ffmpeg/__platform/__linux.py
local_ffmpeg/__platform/__osx.py
local_ffmpeg/__platform/__win.py
local_ffmpeg-0.1.4.dist-info/METADATA
local_ffmpeg-0.1.4.dist-info/WHEEL
local_ffmpeg-0.1.4.dist-info/entry_points.txt
local_ffmpeg-0.1.4.dist-info/licenses/LICENSE
local_ffmpeg-0.1.4.dist-info/RECORD
