Metadata-Version: 2.4
Name: local-ffmpeg
Version: 0.1.4
Summary: Python utility that automatically downloads and installs FFmpeg binaries locally for your project
Project-URL: Homepage, https://github.com/atsuiyo/local-ffmpeg
Project-URL: Bug Tracker, https://github.com/atsuiyo/local-ffmpeg/issues
License-File: LICENSE
Classifier: Development Status :: 4 - Beta
Classifier: Intended Audience :: Developers
Classifier: License :: OSI Approved :: MIT License
Classifier: Operating System :: Microsoft :: Windows
Classifier: Operating System :: POSIX :: Linux
Classifier: Programming Language :: Python :: 3
Classifier: Topic :: Multimedia :: Sound/Audio
Classifier: Topic :: Multimedia :: Video
Requires-Python: >=3.6
Requires-Dist: requests>=2.25.0
Requires-Dist: tqdm>=4.50.0
